bsonjs.pyd
python_bsonjs-0.7.0.dist-info/licenses/LICENSE
python_bsonjs-0.7.0.dist-info/METADATA
python_bsonjs-0.7.0.dist-info/WHEEL
python_bsonjs-0.7.0.dist-info/top_level.txt
python_bsonjs-0.7.0.dist-info/RECORD
