Metadata-Version: 2.4
Name: python-bsonjs
Version: 0.7.0
Summary: A library for converting between BSON and JSON.
Author-email: Shane Harvey <shane.harvey@mongodb.com>
License:                                  Apache License
Project-URL: Homepage, https://github.com/mongodb-labs/python-bsonjs
Keywords: BSON,JSON,PyMongo
Classifier: Development Status :: 4 - Beta
Classifier: Intended Audience :: Developers
Classifier: License :: OSI Approved :: Apache Software License
Classifier: Operating System :: MacOS :: MacOS X
Classifier: Operating System :: Microsoft :: Windows
Classifier: Operating System :: POSIX
Classifier: Programming Language :: Python :: 3
Classifier: Programming Language :: Python :: 3 :: Only
Classifier: Programming Language :: Python :: 3.9
Classifier: Programming Language :: Python :: Implementation :: CPython
Classifier: Programming Language :: Python :: 3.10
Classifier: Programming Language :: Python :: 3.11
Classifier: Programming Language :: Python :: 3.12
Classifier: Programming Language :: Python :: 3.13
Classifier: Programming Language :: Python :: 3.14
Requires-Python: >=3.9
License-File: LICENSE
Provides-Extra: test
Requires-Dist: pymongo>=4; extra == "test"
Requires-Dist: pytest; extra == "test"
Dynamic: license-file
